{
  "blog": [
    {
      "username": "ddertiппп",
      "title": "Краєвидb",
      "content": "Фото природи",
      "imageUrl": "https://content.rozetka.com.ua/goods/images/big/17813412.jpg",
      "updatedAt": "2025-08-02T13:24:46.274Z",
      "id": "1"
    },
    {
      "id": "2",
      "username": "kirill",
      "title": "Озеро",
      "content": "Дуже гарне озеро",
      "imageUrl": "https://vandrivka.com.ua/wp-content/uploads/2017/08/Ozero-Vidro-Kiyiv-9.jpg"
    },
    {
      "id": "3",
      "username": "pro100mq",
      "title": "Гори",
      "content": "Гори",
      "imageUrl": "https://media.dyvys.info/2017/05/mountains-1366x768-006.jpg"
    },
    {
      "id": "5",
      "username": "hahtech",
      "title": "Нічне фото",
      "content": "Все видно",
      "imageUrl": "https://i.photographers.ua/images/pictures/37255/0_5_dsc_3837.jpg"
    },
    {
      "id": "54b1",
      "username": "asd",
      "title": "asd",
      "content": "asd",
      "imageUrl": "https://encrypted-tbn0.gstatic.com/images?q=tbn:ANd9GcQLU0t2tiomu0cgZPwXhyHKpykixhpzsfOlJQ&s"
    }
  ]
}